ipywidget_gallery/__init__.py
ipywidget_gallery/checkbox.py
ipywidget_gallery/colorpicker.py
ipywidget_gallery/datepicker.py
ipywidget_gallery/dropdown.py
ipywidget_gallery/filepicker.py
ipywidget_gallery/gallery.py
ipywidget_gallery/intslider.py
ipywidget_gallery/radiobuttons.py
ipywidget_gallery/rangeslider.py
ipywidget_gallery/selectmultiple.py
ipywidget_gallery/textarea.py
ipywidget_gallery/togglebutton.py
ipywidget_gallery/togglebuttongroup.py
ipywidgets_gallery/__init__.py
ipywidgets_gallery/checkbox.py
ipywidgets_gallery/colorpicker.py
ipywidgets_gallery/datepicker.py
ipywidgets_gallery/dropdown.py
ipywidgets_gallery/filepicker.py
ipywidgets_gallery/gallery.py
ipywidgets_gallery/intslider.py
ipywidgets_gallery/radiobuttons.py
ipywidgets_gallery/rangeslider.py
ipywidgets_gallery/selectmultiple.py
ipywidgets_gallery/textarea.py
ipywidgets_gallery/togglebutton.py
ipywidgets_gallery/togglebuttongroup.py
tests/__init__.py
tests/test_all.py
tests/test_ipywidgets_gallery.py
ipywidgets_gallery-0.17.dist-info/METADATA
ipywidgets_gallery-0.17.dist-info/WHEEL
ipywidgets_gallery-0.17.dist-info/top_level.txt
ipywidgets_gallery-0.17.dist-info/RECORD
