Metadata-Version: 2.1
Name: ipywidgets-gallery
Version: 0.17
Summary: A library of interactive widgets for Jupyter notebooks
Home-page: https://github.com/lsternlicht/ipywidgets_gallery
Author: Leo Sternlicht
Author-email: leo@sternlicht.org
License: MIT
Classifier: Development Status :: 3 - Alpha
Classifier: Intended Audience :: Developers
Classifier: License :: OSI Approved :: MIT License
Classifier: Programming Language :: Python :: 3
Classifier: Programming Language :: Python :: 3.6
Classifier: Programming Language :: Python :: 3.7
Classifier: Programming Language :: Python :: 3.8
Classifier: Programming Language :: Python :: 3.9
Classifier: Programming Language :: Python :: 3.10
Requires-Dist: ipywidgets (>=7.6.3)
